numpyworld/__init__.py
numpyworld/main.py
numpyworld/test_main.py
numpyworld-0.3.dist-info/METADATA
numpyworld-0.3.dist-info/WHEEL
numpyworld-0.3.dist-info/top_level.txt
numpyworld-0.3.dist-info/RECORD
