Metadata-Version: 2.1
Name: numpyworld
Version: 0.3
Summary: Use numpy to create a world that you dreamed about!
Home-page: https://github.com/yingshaoxo/numpyworld
Author: yingshaoxo
Author-email: yingshaoxo@gmail.com
License: MIT
Keywords: numpyworld
Platform: UNKNOWN
Classifier: Operating System :: POSIX :: Linux
Classifier: Programming Language :: Python :: 3
Classifier: Topic :: System
Classifier: License :: OSI Approved :: MIT License
Requires-Dist: setuptools
Requires-Dist: numpy
Requires-Dist: matplotlib
Requires-Dist: pillow
Requires-Dist: moviepy
Provides-Extra: animation
Requires-Dist: pygame ; extra == 'animation'
